viv-2024.1005.dist-info/METADATA
viv-2024.1005.dist-info/WHEEL
viv-2024.1005.dist-info/entry_points.txt
viv-2024.1005.dist-info/licenses/LICENSE
viv/__init__.py
viv/__main__.py
viv/viv.py
viv-2024.1005.dist-info/RECORD
