Metadata-Version: 2.1
Name: viv
Version: 2024.1005
Summary: viv isn't venv
Home-page: https://github.com/daylinmorgan/viv
Author-Email: Daylin Morgan <daylinmorgan@gmail.com>
License: MIT
Project-URL: Homepage, https://github.com/daylinmorgan/viv
Project-URL: Repository, https://github.com/daylinmorgan/viv
Requires-Python: >=3.8
